ezctl/__init__.py
ezctl/commands/__init__.py
ezctl/commands/check.py
ezctl/commands/deploy.py
ezctl/commands/terminate.py
ezctl/commons/__init__.py
ezctl/commons/common.py
ezctl/main.py
ezctl-0.2.1.dist-info/METADATA
ezctl-0.2.1.dist-info/WHEEL
ezctl-0.2.1.dist-info/entry_points.txt
ezctl-0.2.1.dist-info/RECORD
